{
  "gitSyncId": "6720a55c4e2d48287e4a3a67_ba0c97cf-81df-47cc-b4e5-96389ec5860d",
  "id": "EditReelDetails_api_patch_reel_titles",
  "pluginId": "restapi-plugin",
  "pluginType": "API",
  "unpublishedAction": {
    "actionConfiguration": {
      "autoGeneratedHeaders": [
        {
          "key": "content-type",
          "value": "application/json"
        }
      ],
      "body": "{\n\t\"en\": {{input_title_en.text}},\n\t\"zhCn\": {{input_title_sc.text}},\n\t\"zhHk\": {{input_title_tc.text}}\n}",
      "bodyFormData": [],
      "encodeParamsToggle": true,
      "formData": {
        "apiContentType": "none"
      },
      "headers": [
        {
          "key": "Authorization",
          "value": "Bearer {{appsmith.store.testAdminToken}}"
        }
      ],
      "httpMethod": "PATCH",
      "httpVersion": "HTTP11",
      "paginationType": "NONE",
      "path": "{{appsmith.store.testApiRoot}}/reels/admin/reels/{{appsmith.URL.queryParams.id}}/titles",
      "pluginSpecifiedTemplates": [
        {
          "value": true
        }
      ],
      "queryParameters": [],
      "timeoutInMillisecond": 10000
    },
    "confirmBeforeExecute": false,
    "datasource": {
      "datasourceConfiguration": {
        "url": ""
      },
      "isAutoGenerated": false,
      "name": "DEFAULT_REST_DATASOURCE",
      "pluginId": "restapi-plugin"
    },
    "dynamicBindingPathList": [
      {
        "key": "path"
      },
      {
        "key": "headers[0].value"
      },
      {
        "key": "body"
      }
    ],
    "executeOnLoad": false,
    "name": "api_patch_reel_titles",
    "pageId": "EditReelDetails",
    "userSetOnLoad": false
  }
}